gdrf/__init__.py
gdrf/__main__.py
gdrf/cli.py
gdrf/infer/__init__.py
gdrf/infer/divergence.py
gdrf/infer/gvi.py
gdrf/infer/loss.py
gdrf/models/__init__.py
gdrf/models/abstract_gdrf.py
gdrf/models/categorical.py
gdrf/models/gdrf.py
gdrf/models/sparse_gdrf.py
gdrf/models/topic_model.py
gdrf/models/utils.py
gdrf/train_script.py
gdrf/utils/__init__.py
gdrf/utils/callbacks.py
gdrf/utils/general.py
gdrf/utils/loggers.py
gdrf/utils/wandblogger.py
gdrf/visualize/__init__.py
gdrf-0.1.7.dist-info/entry_points.txt
gdrf-0.1.7.dist-info/LICENSE
gdrf-0.1.7.dist-info/WHEEL
gdrf-0.1.7.dist-info/METADATA
gdrf-0.1.7.dist-info/RECORD
