Metadata-Version: 2.1
Name: gdrf
Version: 0.1.7
Summary: Pytorch+GPytorch implementation of GDRFs from San Soucie et al. 2020.
Home-page: https://github.com/san-soucie/gdrf
License: GPL3
Author: John San Soucie
Author-email: jsansoucie@whoi.edu
Requires-Python: >=3.8.0,<3.11
Classifier: Development Status :: 2 - Pre-Alpha
Classifier: Intended Audience :: Developers
Classifier: License :: OSI Approved :: MIT License
Classifier: License :: Other/Proprietary License
Classifier: Natural Language :: English
Classifier: Programming Language :: Python :: 3
Classifier: Programming Language :: Python :: 3.10
Classifier: Programming Language :: Python :: 3.6
Classifier: Programming Language :: Python :: 3.7
Classifier: Programming Language :: Python :: 3.8
Classifier: Programming Language :: Python :: 3.9
Provides-Extra: dev
Provides-Extra: doc
Provides-Extra: test
Requires-Dist: black (>=20.8b1,<21.0); extra == "test"
Requires-Dist: fire (>=0.4.0,<0.5.0)
Requires-Dist: flake8 (>=3.8.4,<4.0.0); extra == "test"
Requires-Dist: flake8-docstrings (>=1.6.0,<2.0.0); extra == "test"
Requires-Dist: gpytorch (>=1.5.0,<2.0.0)
Requires-Dist: holoviews (>=1.14.6,<2.0.0)
Requires-Dist: hvplot (>=0.7.3,<0.8.0)
Requires-Dist: isort (>=5.6.4,<6.0.0); extra == "test"
Requires-Dist: matplotlib (>=3.4.2,<4.0.0)
Requires-Dist: mkdocs (>=1.1.2,<2.0.0); extra == "doc"
Requires-Dist: mkdocs-autorefs (==0.1.1); extra == "doc"
Requires-Dist: mkdocs-include-markdown-plugin (>=1.0.0,<2.0.0); extra == "doc"
Requires-Dist: mkdocs-material (>=6.1.7,<7.0.0); extra == "doc"
Requires-Dist: mkdocs-material-extensions (>=1.0.1,<2.0.0)
Requires-Dist: mkdocstrings (>=0.15.2,<0.16.0); extra == "doc"
Requires-Dist: numpy (>=1.21.0,<2.0.0)
Requires-Dist: pandas (<1.3.0)
Requires-Dist: pillow (>=8.3.2,<9.0.0)
Requires-Dist: pip (>=20.3.1,<21.0.0); extra == "dev"
Requires-Dist: plotly (>=5.2.2,<6.0.0)
Requires-Dist: poetry (>=1.1.10,<2.0.0); extra == "dev"
Requires-Dist: pre-commit (>=2.12.0,<3.0.0); extra == "dev"
Requires-Dist: pyro-ppl (>=1.6.0,<2.0.0)
Requires-Dist: pytest (>=6.1.2,<7.0.0); extra == "test"
Requires-Dist: pytest-cov (>=2.10.1,<3.0.0); extra == "test"
Requires-Dist: pyyaml (>=5.4.0,<6.0.0)
Requires-Dist: scipy (>=1.7.0,<2.0.0)
Requires-Dist: toml (>=0.10.2,<0.11.0); extra == "dev"
Requires-Dist: torch (>=1.9.0,<2.0.0)
Requires-Dist: torchvision (>=0.10.0,<0.11.0)
Requires-Dist: tox (>=3.20.1,<4.0.0); extra == "dev"
Requires-Dist: tqdm (>=4.61.1,<5.0.0)
Requires-Dist: twine (>=3.3.0,<4.0.0); extra == "dev"
Requires-Dist: virtualenv (>=20.2.2,<21.0.0); extra == "dev"
Requires-Dist: wandb (>=0.12.0,<0.13.0); extra == "doc"
